tips_cli/__init__.py
tips_cli/__main__.py
tips_cli/config.py
tips_cli/editor_launcher.py
tips_cli/file_manager.py
tips_cli/main.py
tips_cli/tracker.py
tips_cli/utils.py
tips_cli_tool-0.1.2.dist-info/licenses/LICENSE
tips_cli_tool-0.1.2.dist-info/METADATA
tips_cli_tool-0.1.2.dist-info/WHEEL
tips_cli_tool-0.1.2.dist-info/entry_points.txt
tips_cli_tool-0.1.2.dist-info/top_level.txt
tips_cli_tool-0.1.2.dist-info/RECORD
