Metadata-Version: 2.4
Name: tips-cli-tool
Version: 0.1.2
Summary: A simple CLI tool for creating temporary notes that are automatically deleted after editing.
Author-email: Kevin589981 <kevin3627713@gmail.com>
License-Expression: MIT
Project-URL: Homepage, https://github.com/Kevin589981/tips-python
Classifier: Programming Language :: Python :: 3
Classifier: Operating System :: OS Independent
Requires-Python: >=3.6
License-File: LICENSE
Requires-Dist: PyYAML
Dynamic: license-file
